[
    {
        "condition": "{'Dependents': 'No', 'RaceEthnicity': 'White or of European descent'}",
        "treatment": "{'Exercise': '3 - 4 times per week', 'FormalEducation': 'Bachelor\u2019s degree (BA, BS, B.Eng., etc.)'}",
        "utility": 28023.76,
        "protected_utility": 22140.16,
        "unprotected_utility": 26877.64,
        "coverage_rate": 54.46,
        "protected_coverage_rate": 39.46,
        "pvals": {
            "all": [
                0.002838712307766086
            ],
            "protected": [
                0.02998905683811309
            ],
            "non-protected": [
                0.012131210963489588
            ]
        }
    },
    {
        "condition": "{'Student': 'No', 'RaceEthnicity': 'White or of European descent'}",
        "treatment": "{'Exercise': '3 - 4 times per week', 'UndergradMajor': 'Computer science, computer engineering, or software engineering'}",
        "utility": 17897.89,
        "protected_utility": 20512.27,
        "unprotected_utility": 15872.53,
        "coverage_rate": 66.81,
        "protected_coverage_rate": 39.76,
        "pvals": {
            "all": [
                0.02902841657568152
            ],
            "protected": [
                0.02486236510477796
            ],
            "non-protected": [
                0.0818437908509346
            ]
        }
    },
    {
        "condition": "{'Gender': 'Male', 'Dependents': 'No'}",
        "treatment": "{'Exercise': '3 - 4 times per week', 'UndergradMajor': 'Computer science, computer engineering, or software engineering'}",
        "utility": 23014.54,
        "protected_utility": 17290.11,
        "unprotected_utility": 20785.64,
        "coverage_rate": 63.16,
        "protected_coverage_rate": 65.13,
        "pvals": {
            "all": [
                0.005336102828362257
            ],
            "protected": [
                0.04586306851192543
            ],
            "non-protected": [
                0.0376234274278322
            ]
        }
    },
    {
        "condition": "{'Age': '25 - 34 years old', 'SexualOrientation': 'Straight or heterosexual'}",
        "treatment": "{'FormalEducation': 'Bachelor\u2019s degree (BA, BS, B.Eng., etc.)', 'Hobby': 'Yes'}",
        "utility": 10711.96,
        "protected_utility": 8897.49,
        "unprotected_utility": 0.0,
        "coverage_rate": 49.81,
        "protected_coverage_rate": 56.44,
        "pvals": {
            "all": [
                0.09891521496921911
            ],
            "protected": [
                0.0599198380895923
            ],
            "non-protected": [
                0.11909434673037109
            ]
        }
    },
    {
        "condition": "{'Dependents': 'No'}",
        "treatment": "{'Exercise': '3 - 4 times per week', 'UndergradMajor': 'Computer science, computer engineering, or software engineering'}",
        "utility": 20673.52,
        "protected_utility": 17536.45,
        "unprotected_utility": 17653.75,
        "coverage_rate": 69.77,
        "protected_coverage_rate": 69.58,
        "pvals": {
            "all": [
                0.008225568135083397
            ],
            "protected": [
                0.03239479971360417
            ],
            "non-protected": [
                0.06027109032936384
            ]
        }
    },
    {
        "condition": "{'Gender': 'Male', 'Student': 'No', 'RaceEthnicity': 'White or of European descent'}",
        "treatment": "{'Exercise': '3 - 4 times per week', 'UndergradMajor': 'Computer science, computer engineering, or software engineering'}",
        "utility": 18644.99,
        "protected_utility": 20690.2,
        "unprotected_utility": 16472.21,
        "coverage_rate": 61.64,
        "protected_coverage_rate": 37.21,
        "pvals": {
            "all": [
                0.03213251892525257
            ],
            "protected": [
                0.034205564312267074
            ],
            "non-protected": [
                0.08916118819337812
            ]
        }
    },
    {
        "condition": "{'Gender': 'Male', 'Age': '25 - 34 years old', 'SexualOrientation': 'Straight or heterosexual'}",
        "treatment": "{'FormalEducation': 'Bachelor\u2019s degree (BA, BS, B.Eng., etc.)', 'Hobby': 'Yes'}",
        "utility": 12061.86,
        "protected_utility": 8800.9,
        "unprotected_utility": 15101.23,
        "coverage_rate": 46.92,
        "protected_coverage_rate": 53.4,
        "pvals": {
            "all": [
                0.06849559124771674
            ],
            "protected": [
                0.07672970028819351
            ],
            "non-protected": [
                0.07313074013392917
            ]
        }
    },
    {
        "condition": "{'Gender': 'Male', 'Dependents': 'No', 'Student': 'No'}",
        "treatment": "{'Exercise': '3 - 4 times per week', 'UndergradMajor': 'Computer science, computer engineering, or software engineering'}",
        "utility": 23407.28,
        "protected_utility": 25121.89,
        "unprotected_utility": 20600.17,
        "coverage_rate": 51.99,
        "protected_coverage_rate": 46.55,
        "pvals": {
            "all": [
                0.011104913891567049
            ],
            "protected": [
                0.017925172942613705
            ],
            "non-protected": [
                0.0574952928425224
            ]
        }
    },
    {
        "condition": "{'Dependents': 'No', 'Student': 'No'}",
        "treatment": "{'Exercise': '3 - 4 times per week', 'UndergradMajor': 'Computer science, computer engineering, or software engineering'}",
        "utility": 21277.29,
        "protected_utility": 24765.62,
        "unprotected_utility": 18089.52,
        "coverage_rate": 57.52,
        "protected_coverage_rate": 49.95,
        "pvals": {
            "all": [
                0.014225611147529989
            ],
            "protected": [
                0.012811966240173438
            ],
            "non-protected": [
                0.07488443178656144
            ]
        }
    }
]